README.md
setup.py
forgery/__init__.py
forgery/detector.py
forgery.egg-info/PKG-INFO
forgery.egg-info/SOURCES.txt
forgery.egg-info/dependency_links.txt
forgery.egg-info/top_level.txt