Metadata-Version: 2.1
Name: forgery
Version: 0.0.1
Summary: Forgery and Fabrication Detection using ML.
Home-page: https://github.com/YuP0ra/forgery
Author: AbdElAziz Moftah
Author-email: abdelazizimoftah@gmail.com
License: UNKNOWN
Platform: UNKNOWN
Classifier: Programming Language :: Python :: 3
Classifier: License :: OSI Approved :: MIT License
Classifier: Operating System :: OS Independent
Requires-Python: >=3.6
